sdgrpcserver/__init__.py
sdgrpcserver/manager.py
sdgrpcserver/server.py
sdgrpcserver/utils.py
sdgrpcserver/generated/__init__.py
sdgrpcserver/generated/completion_pb2.py
sdgrpcserver/generated/completion_pb2_grpc.py
sdgrpcserver/generated/dashboard_pb2.py
sdgrpcserver/generated/dashboard_pb2_grpc.py
sdgrpcserver/generated/engines_pb2.py
sdgrpcserver/generated/engines_pb2_grpc.py
sdgrpcserver/generated/generation_pb2.py
sdgrpcserver/generated/generation_pb2_grpc.py
sdgrpcserver/pipeline/__init__.py
sdgrpcserver/pipeline/safety_checkers.py
sdgrpcserver/pipeline/scheduling_ddim.py
sdgrpcserver/pipeline/scheduling_euler_ancestral_discrete.py
sdgrpcserver/pipeline/scheduling_euler_discrete.py
sdgrpcserver/pipeline/unified_pipeline.py
sdgrpcserver/services/__init__.py
sdgrpcserver/services/dashboard.py
sdgrpcserver/services/engines.py
sdgrpcserver/services/generate.py
sdgrpcserver/sonora/__init__.py
sdgrpcserver/sonora/__version__.py
sdgrpcserver/sonora/aio.py
sdgrpcserver/sonora/asgi.py
sdgrpcserver/sonora/client.py
sdgrpcserver/sonora/echotest.py
sdgrpcserver/sonora/protocol.py
sdgrpcserver/sonora/wsgi.py
stable_diffusion_grpcserver-0.0.1.dist-info/entry_points.txt
stable_diffusion_grpcserver-0.0.1.dist-info/LICENSE
stable_diffusion_grpcserver-0.0.1.dist-info/WHEEL
stable_diffusion_grpcserver-0.0.1.dist-info/METADATA
stable_diffusion_grpcserver-0.0.1.dist-info/RECORD
