Metadata-Version: 2.1
Name: stable-diffusion-grpcserver
Version: 0.0.1
Summary: A local Stable Diffusion AI image generation server compatible with the Stability-AI GRPC protocol'
Author-email: Hamish Friedlander <hafriedlander@gmail.com>
Classifier: License :: OSI Approved :: Apache Software License
Requires-Dist: torch ~= 1.12.1
Requires-Dist: torchvision ~= 0.13.1
Requires-Dist: numpy ~= 1.23.3
Requires-Dist: opencv-python ~= 4.6.0.66
Requires-Dist: scipy ~= 1.9.1
Requires-Dist: transformers ~= 4.22.1
Requires-Dist: diffusers
Requires-Dist: protobuf~=3.20
Requires-Dist: grpcio~=1.48.1
Requires-Dist: Flask~=2.2.2
Requires-Dist: wsgicors~=0.7.0
Requires-Dist: waitress~=2.1.2
Requires-Dist: hupper~=1.10.3
Requires-Dist: watchdog ~= 2.1.9
Project-URL: Home, https://github.com/hafriedlander/stable-diffusion-grpcserver
